fluxcalc/__init__.py
fluxcalc/cleandata.py
fluxcalc/heat.py
fluxcalc/io.py
fluxcalc/tau.py
fluxcalc/tke.py
fluxcalc-0.1.2.dist-info/METADATA
fluxcalc-0.1.2.dist-info/WHEEL
fluxcalc-0.1.2.dist-info/licenses/LICENSE
fluxcalc-0.1.2.dist-info/RECORD
