Metadata-Version: 2.4
Name: fluxcalc
Version: 0.1.2
Summary: Flexible flux and turbulence calculations from NetCDF files.
Project-URL: Homepage, https://github.com/jpiot1/flux_calculations
Project-URL: Repository, https://github.com/jpiot1/flux_calculations
Author-email: Julie Piot <juliepiot37@gmail.com>
License:                     GNU GENERAL PUBLIC LICENSE
License-File: LICENSE
Classifier: Intended Audience :: Science/Research
Classifier: License :: OSI Approved :: GNU Lesser General Public License v2 or later (LGPLv2+)
Classifier: Programming Language :: Python :: 3
Classifier: Programming Language :: Python :: 3 :: Only
Classifier: Topic :: Scientific/Engineering :: Atmospheric Science
Requires-Python: >=3.9
Requires-Dist: numpy
Requires-Dist: pandas
Requires-Dist: xarray
Provides-Extra: dev
Requires-Dist: build; extra == 'dev'
Requires-Dist: mypy; extra == 'dev'
Requires-Dist: pytest; extra == 'dev'
Requires-Dist: ruff; extra == 'dev'
Requires-Dist: twine; extra == 'dev'
